CHANGES.txt
LICENSE.txt
MANIFEST.in
README.txt
setup.py
js/__init__.py
js.extjs.egg-info/PKG-INFO
js.extjs.egg-info/SOURCES.txt
js.extjs.egg-info/dependency_links.txt
js.extjs.egg-info/entry_points.txt
js.extjs.egg-info/namespace_packages.txt
js.extjs.egg-info/not-zip-safe
js.extjs.egg-info/requires.txt
js.extjs.egg-info/top_level.txt
js/extjs/__init__.py
js/extjs/adapter.py
js/extjs/extjs.py
js/extjs/library.py
js/extjs/test_extjs.txt
js/extjs/theme.py
js/extjs/ux.py
js/extjs/resources/INCLUDE_ORDER.txt
js/extjs/resources/README.txt
js/extjs/resources/ext-all-debug-w-comments.js
js/extjs/resources/ext-all-debug.js
js/extjs/resources/ext-all.js
js/extjs/resources/gpl-3.0.txt
js/extjs/resources/index.html
js/extjs/resources/license.txt
js/extjs/resources/adapter/ext/ext-base-debug.js
js/extjs/resources/adapter/ext/ext-base.js
js/extjs/resources/examples/ux/BufferView.js
js/extjs/resources/examples/ux/CenterLayout.js
js/extjs/resources/examples/ux/CheckColumn.js
js/extjs/resources/examples/ux/ColumnHeaderGroup.js
js/extjs/resources/examples/ux/ColumnNodeUI.js
js/extjs/resources/examples/ux/DataView-more.js
js/extjs/resources/examples/ux/DataViewTransition.js
js/extjs/resources/examples/ux/FieldLabeler.js
js/extjs/resources/examples/ux/FieldReplicator.js
js/extjs/resources/examples/ux/Focus.js
js/extjs/resources/examples/ux/GMapPanel.js
js/extjs/resources/examples/ux/GroupSummary.js
js/extjs/resources/examples/ux/GroupTab.js
js/extjs/resources/examples/ux/GroupTabPanel.js
js/extjs/resources/examples/ux/ItemSelector.js
js/extjs/resources/examples/ux/LockingGridView.js
js/extjs/resources/examples/ux/MultiSelect.js
js/extjs/resources/examples/ux/PagingMemoryProxy.js
js/extjs/resources/examples/ux/PanelResizer.js
js/extjs/resources/examples/ux/Portal.js
js/extjs/resources/examples/ux/PortalColumn.js
js/extjs/resources/examples/ux/Portlet.js
js/extjs/resources/examples/ux/ProgressBarPager.js
js/extjs/resources/examples/ux/Reorderer.js
js/extjs/resources/examples/ux/RowEditor.js
js/extjs/resources/examples/ux/RowExpander.js
js/extjs/resources/examples/ux/RowLayout.js
js/extjs/resources/examples/ux/SearchField.js
js/extjs/resources/examples/ux/SelectBox.js
js/extjs/resources/examples/ux/SlidingPager.js
