Metadata-Version: 1.0
Name: js.extjs
Version: 3.3.1
Summary: Fanstatic packaging of ExtJS
Home-page: UNKNOWN
Author: Fanstatic Developers
Author-email: fanstatic@googlegroups.com
License: BSD
Platform: UNKNOWN
